LICENSE
MANIFEST.in
README.md
setup.py
archivebox/.flake8
archivebox/LICENSE
archivebox/README.md
archivebox/__init__.py
archivebox/__main__.py
archivebox/config.py
archivebox/config_stubs.py
archivebox/logging_util.py
archivebox/main.py
archivebox/manage.py
archivebox/mypy.ini
archivebox/package.json
archivebox/system.py
archivebox/util.py
archivebox/cli/__init__.py
archivebox/cli/archivebox_add.py
archivebox/cli/archivebox_config.py
archivebox/cli/archivebox_help.py
archivebox/cli/archivebox_init.py
archivebox/cli/archivebox_list.py
archivebox/cli/archivebox_manage.py
archivebox/cli/archivebox_oneshot.py
archivebox/cli/archivebox_remove.py
archivebox/cli/archivebox_schedule.py
archivebox/cli/archivebox_server.py
archivebox/cli/archivebox_setup.py
archivebox/cli/archivebox_shell.py
archivebox/cli/archivebox_status.py
archivebox/cli/archivebox_update.py
archivebox/cli/archivebox_version.py
archivebox/cli/tests.py
archivebox/core/__init__.py
archivebox/core/admin.py
archivebox/core/apps.py
archivebox/core/forms.py
archivebox/core/middleware.py
archivebox/core/mixins.py
archivebox/core/models.py
archivebox/core/settings.py
archivebox/core/tests.py
archivebox/core/urls.py
archivebox/core/views.py
archivebox/core/welcome_message.py
archivebox/core/wsgi.py
archivebox/core/management/commands/archivebox.py
archivebox/core/migrations/0001_initial.py
archivebox/core/migrations/0002_auto_20200625_1521.py
archivebox/core/migrations/0003_auto_20200630_1034.py
archivebox/core/migrations/0004_auto_20200713_1552.py
archivebox/core/migrations/0005_auto_20200728_0326.py
archivebox/core/migrations/0006_auto_20201012_1520.py
archivebox/core/migrations/0007_archiveresult.py
archivebox/core/migrations/0008_auto_20210105_1421.py
archivebox/core/migrations/0009_auto_20210216_1038.py
archivebox/core/migrations/0010_auto_20210216_1055.py
archivebox/core/migrations/0011_auto_20210216_1331.py
archivebox/core/migrations/0012_auto_20210216_1425.py
archivebox_likn.egg-info/PKG-INFO
archivebox_likn.egg-info/SOURCES.txt
archivebox_likn.egg-info/dependency_links.txt
archivebox_likn.egg-info/entry_points.txt
archivebox_likn.egg-info/requires.txt
archivebox_likn.egg-info/top_level.txt