Metadata-Version: 2.1
Name: archivebox-likn
Version: 0.6.3
Summary: The decentralized hosted internet archive.
Home-page: https://github.com/ArchiveBox/ArchiveBox
Author: Nick Sweeting
Author-email: git@nicksweeting.com
License: MIT
Project-URL: Source, https://github.com/ArchiveBox/ArchiveBox
Project-URL: Documentation, https://github.com/ArchiveBox/ArchiveBox/wiki
Project-URL: Bug Tracker, https://github.com/ArchiveBox/ArchiveBox/issues
Project-URL: Changelog, https://github.com/ArchiveBox/ArchiveBox/releases
Project-URL: Roadmap, https://github.com/ArchiveBox/ArchiveBox/wiki/Roadmap
Project-URL: Community, https://github.com/ArchiveBox/ArchiveBox/wiki/Web-Archiving-Community
Project-URL: Demo, https://demo.archivebox.io
Project-URL: Donate, https://github.com/ArchiveBox/ArchiveBox/wiki/Donations
Platform: UNKNOWN
Classifier: License :: OSI Approved :: MIT License
Classifier: Natural Language :: English
Classifier: Operating System :: OS Independent
Classifier: Development Status :: 4 - Beta
Classifier: Topic :: Utilities
Classifier: Topic :: System :: Archiving
Classifier: Topic :: System :: Archiving :: Backup
Classifier: Topic :: System :: Recovery Tools
Classifier: Topic :: Sociology :: History
Classifier: Topic :: Internet :: WWW/HTTP
Classifier: Topic :: Internet :: WWW/HTTP :: Indexing/Search
Classifier: Topic :: Internet :: WWW/HTTP :: WSGI :: Application
Classifier: Topic :: Software Development :: Libraries :: Python Modules
Classifier: Intended Audience :: Developers
Classifier: Intended Audience :: Education
Classifier: Intended Audience :: End Users/Desktop
Classifier: Intended Audience :: Information Technology
Classifier: Intended Audience :: Legal Industry
Classifier: Intended Audience :: System Administrators
Classifier: Environment :: Console
Classifier: Environment :: Web Environment
Classifier: Programming Language :: Python :: 3
Classifier: Programming Language :: Python :: 3.7
Classifier: Programming Language :: Python :: 3.8
Classifier: Programming Language :: Python :: 3.9
Classifier: Framework :: Django
Classifier: Typing :: Typed
Requires-Python: >=3.7
Provides-Extra: sonic
Provides-Extra: dev
License-File: LICENSE
